_openspell
openspell
