Metadata-Version: 1.1
Name: openspell
Version: 0.0.5
Summary: spell checker
Home-page: https://github.com/bakwc/OpenSpell
Author: Filipp Ozinov
Author-email: fippo@mail.ru
License: UNKNOWN
Download-URL: https://github.com/bakwc/OpenSpell/tarball/0.0.5
Keywords: nlp,spell,spell-checker
Platform: UNKNOWN
Classifier: Programming Language :: Python :: 2.7
Classifier: License :: OSI Approved :: MIT License
